my_simple_calculator/__init__.py
my_simple_calculator/calculator.py
simple_calculator_ramzy_elyatim-0.1.0.dist-info/METADATA
simple_calculator_ramzy_elyatim-0.1.0.dist-info/WHEEL
simple_calculator_ramzy_elyatim-0.1.0.dist-info/top_level.txt
simple_calculator_ramzy_elyatim-0.1.0.dist-info/RECORD
