Metadata-Version: 2.4
Name: simple-calculator-ramzy-elyatim
Version: 0.1.0
Summary: A simple calculator package for basic math operations
Home-page: https://github.com/yourusername/simple-calculator-ramzy-elyatim
Author: Ramzy Alytym
Author-email: your.email@example.com
Classifier: Programming Language :: Python :: 3
Classifier: License :: OSI Approved :: MIT License
Classifier: Operating System :: OS Independent
Requires-Python: >=3.6
Dynamic: author
Dynamic: author-email
Dynamic: classifier
Dynamic: description
Dynamic: description-content-type
Dynamic: home-page
Dynamic: requires-python
Dynamic: summary
